director/__init__.py
director/director.py
director/parser.py
pythreader/LogFile.py
pythreader/RWLock.py
pythreader/Scheduler.py
pythreader/Subprocess.py
pythreader/Version.py
pythreader/__init__.py
pythreader/barrier.py
pythreader/core.py
pythreader/dequeue.py
pythreader/escrow.py
pythreader/flag.py
pythreader/gang.py
pythreader/gate.py
pythreader/processor.py
pythreader/producer.py
pythreader/promise.py
pythreader/subprocess_3_11.py
pythreader/task_queue.py
pythreader/tools/__init__.py
pythreader/tools/fswatch.py
tests/chained_processors.py
tests/processor.py
tests/processor_async.py
tests/processors.py
tests/rwlock.py
tests/scheduler.py
tests/task_queue.py
tests/task_queue_stagger.py
tests/tasks_exceptions.py
pythreader-2.15.0.dist-info/LICENSE
pythreader-2.15.0.dist-info/METADATA
pythreader-2.15.0.dist-info/WHEEL
pythreader-2.15.0.dist-info/entry_points.txt
pythreader-2.15.0.dist-info/top_level.txt
pythreader-2.15.0.dist-info/RECORD
